{
  "accounts": [
    {
      "userName": "kewkewkew007",
      "name": "qqqxq",
      "passWord": "30032545",
      "points": 3000,
      "id": 1
    },
    {
      "id": 2,
      "userName": "wave",
      "passWord": "12345",
      "name": "TANAK1Z",
      "points": 2000
    },
    {
      "id": 3,
      "userName": "paul",
      "passWord": "12345",
      "name": "That.pk",
      "points": 5000
    },
    {
      "userName": "Chin",
      "passWord": "123",
      "name": "Chin",
      "points": 1000,
      "id": 5
    },
    {
      "userName": "metha",
      "passWord": "123",
      "name": "Toey",
      "points": 1000,
      "id": 6
    },
    {
      "userName": "yathorn18",
      "name": "neko7687",
      "passWord": "55555",
      "points": 0,
      "id": 7
    }
  ]
}